.DS_Store
opentrons/.DS_Store
opentrons/__init__.py
opentrons/_version.py
opentrons/config/__init__.py
opentrons/config/containers/__init__.py
opentrons/config/containers/default-containers.json
opentrons/config/smoothie/config_one_pro_plus
opentrons/config/smoothie/smoothie-defaults.ini
opentrons/containers/__init__.py
opentrons/containers/calibrator.py
opentrons/containers/persisted_containers.py
opentrons/containers/placeable.py
opentrons/drivers/__init__.py
opentrons/drivers/connection.py
opentrons/drivers/smoothie_drivers/__init__.py
opentrons/drivers/smoothie_drivers/v1_2_0/__init__.py
opentrons/drivers/smoothie_drivers/v1_2_0/driver.py
opentrons/drivers/smoothie_drivers/v1_2_0/virtual_smoothie.py
opentrons/drivers/smoothie_drivers/v2_0_0/__init__.py
opentrons/drivers/smoothie_drivers/v2_0_0/driver.py
opentrons/drivers/smoothie_drivers/v2_0_0/player.py
opentrons/drivers/smoothie_drivers/v2_0_0/virtual_smoothie.py
opentrons/helpers/__init__.py
opentrons/helpers/helpers.py
opentrons/instruments/__init__.py
opentrons/instruments/instrument.py
opentrons/instruments/magbead.py
opentrons/instruments/pipette.py
opentrons/robot/__init__.py
opentrons/robot/command.py
opentrons/robot/robot.py
opentrons/robot/robot2.py
opentrons/server/__init__.py
opentrons/server/helpers.py
opentrons/server/log.py
opentrons/server/main.py
opentrons/server/manager.py
opentrons/server/process_manager.py
opentrons/server/tests/__init__.py
opentrons/server/tests/test_calibration.py
opentrons/server/tests/test_connect_and_diagnostics.py
opentrons/server/tests/test_upload.py
opentrons/server/tests/helpers/__init__.py
opentrons/server/tests/helpers/test_helpers.py
opentrons/util/__init__.py
opentrons/util/environment.py
opentrons/util/log.py
opentrons/util/state.py
opentrons/util/trace.py
opentrons/util/vector.py
openworkstation/.DS_Store
openworkstation/__init__.py
openworkstation/_version.py
openworkstation/__pycache__/__init__.cpython-37.pyc
OpenWorkstation-0.0.1.dist-info/LICENSE
OpenWorkstation-0.0.1.dist-info/METADATA
OpenWorkstation-0.0.1.dist-info/WHEEL
OpenWorkstation-0.0.1.dist-info/top_level.txt
OpenWorkstation-0.0.1.dist-info/RECORD
